gateway_sdk/__init__.py
gateway_sdk/_kosmoy_base.py
gateway_sdk/client.py
gateway_sdk/config.py
gateway_sdk/exceptions.py
gateway_sdk/models.py
gateway_sdk/langchain/__init__.py
gateway_sdk/langchain/client.py
kosmoy_gateway_sdk-0.0.1.dev0.dist-info/METADATA
kosmoy_gateway_sdk-0.0.1.dev0.dist-info/WHEEL
kosmoy_gateway_sdk-0.0.1.dev0.dist-info/top_level.txt
kosmoy_gateway_sdk-0.0.1.dev0.dist-info/RECORD
