Metadata-Version: 2.2
Name: kosmoy-gateway-sdk
Version: 0.0.1.dev0
Summary: A Gateway SDK for making API requests
Author: Olsi Hoxha
Author-email: olsi.hoxha@kosmoy.com
Classifier: Programming Language :: Python :: 3
Classifier: License :: OSI Approved :: MIT License
Classifier: Operating System :: OS Independent
Requires-Python: >=3.7
Requires-Dist: pydantic>=2.5.2
Requires-Dist: requests>=2.31.0
Requires-Dist: openai>=1.57.2
Requires-Dist: python-dotenv>=1.0.1
Provides-Extra: langchain
Requires-Dist: langchain-openai==0.2.12; extra == "langchain"
Dynamic: author
Dynamic: author-email
Dynamic: classifier
Dynamic: description
Dynamic: description-content-type
Dynamic: provides-extra
Dynamic: requires-dist
Dynamic: requires-python
Dynamic: summary
